Metadata-Version: 1.0
Name: beta-plotter
Version: 0.0.1
Summary: Package to plot graphs of equations
Home-page: UNKNOWN
Author: Swayam Singh
Author-email: UNKNOWN
License: UNKNOWN
Platform: UNKNOWN
